jupyter_repo2docker-2025.8.0.dist-info/licenses/LICENSE
repo2docker/__init__.py
repo2docker/__main__.py
repo2docker/_version.py
repo2docker/app.py
repo2docker/docker.py
repo2docker/engine.py
repo2docker/semver.py
repo2docker/utils.py
repo2docker/buildpacks/__init__.py
repo2docker/buildpacks/_r_base.py
repo2docker/buildpacks/base.py
repo2docker/buildpacks/docker.py
repo2docker/buildpacks/python3-login
repo2docker/buildpacks/r.py
repo2docker/buildpacks/repo2docker-entrypoint
repo2docker/buildpacks/conda/__init__.py
repo2docker/buildpacks/conda/activate-conda.sh
repo2docker/buildpacks/conda/environment.py-2.7-linux-64.lock
repo2docker/buildpacks/conda/environment.py-2.7.yml
repo2docker/buildpacks/conda/environment.py-3.10-linux-64.lock
repo2docker/buildpacks/conda/environment.py-3.10-linux-aarch64.lock
repo2docker/buildpacks/conda/environment.py-3.10.yml
repo2docker/buildpacks/conda/environment.py-3.11-linux-64.lock
repo2docker/buildpacks/conda/environment.py-3.11-linux-aarch64.lock
repo2docker/buildpacks/conda/environment.py-3.11.lock
repo2docker/buildpacks/conda/environment.py-3.11.yml
repo2docker/buildpacks/conda/environment.py-3.12-linux-64.lock
repo2docker/buildpacks/conda/environment.py-3.12-linux-aarch64.lock
repo2docker/buildpacks/conda/environment.py-3.12.yml
repo2docker/buildpacks/conda/environment.py-3.5-linux-64.lock
repo2docker/buildpacks/conda/environment.py-3.5.yml
repo2docker/buildpacks/conda/environment.py-3.6-linux-64.lock
repo2docker/buildpacks/conda/environment.py-3.6.yml
repo2docker/buildpacks/conda/environment.py-3.7-linux-64.lock
repo2docker/buildpacks/conda/environment.py-3.7-linux-aarch64.lock
repo2docker/buildpacks/conda/environment.py-3.7.yml
repo2docker/buildpacks/conda/environment.py-3.8-linux-64.lock
repo2docker/buildpacks/conda/environment.py-3.8-linux-aarch64.lock
repo2docker/buildpacks/conda/environment.py-3.8.yml
repo2docker/buildpacks/conda/environment.py-3.9-linux-64.lock
repo2docker/buildpacks/conda/environment.py-3.9-linux-aarch64.lock
jupyter_repo2docker-2025.8.0.dist-info/METADATA
jupyter_repo2docker-2025.8.0.dist-info/WHEEL
jupyter_repo2docker-2025.8.0.dist-info/entry_points.txt
jupyter_repo2docker-2025.8.0.dist-info/top_level.txt
jupyter_repo2docker-2025.8.0.dist-info/RECORD
